[{"host": "elpais.com/mexico", "url": "https://elpais.com/mexico/?ed=mex", "last_not_empty_rss": "2024-06-05 11:50:30.256821", "last_filtered_by_keywords": "2024-06-05 02:10:33.915570", "last_approved_news": null, "last_success_parsing": null, "last_success_publishing": null}, {"host": "eurogamer.net", "url": "https://www.eurogamer.net/", "last_not_empty_rss": "2024-06-05 11:50:31.216242", "last_filtered_by_keywords": "2024-06-04 17:10:24.749640", "last_approved_news": "2024-06-04 10:00:33.121116", "last_success_parsing": "2024-06-04 10:00:51.960218", "last_success_publishing": "2024-06-04 10:00:59.449701"}, {"host": "foreignpolicy.com", "url": "https://foreignpolicy.com/", "last_not_empty_rss": "2024-06-05 11:50:31.460354", "last_filtered_by_keywords": null, "last_approved_news": null, "last_success_parsing": null, "last_success_publishing": null}, {"host": "lada.kz", "url": "https://www.lada.kz/", "last_not_empty_rss": "2024-06-05 11:50:31.722578", "last_filtered_by_keywords": "2024-06-05 06:40:26.356791", "last_approved_news": "2024-06-01 22:20:41.683916", "last_success_parsing": "2024-06-01 22:20:59.047689", "last_success_publishing": "2024-06-01 22:21:06.025131"}, {"host": "foxnews.com", "url": "https://www.foxnews.com/", "last_not_empty_rss": "2024-06-05 11:50:31.991908", "last_filtered_by_keywords": "2024-06-05 09:50:29.480444", "last_approved_news": null, "last_success_parsing": null, "last_success_publishing": null}, {"host": "gamesindustry.biz", "url": "https://www.gamesindustry.biz/", "last_not_empty_rss": "2024-06-05 11:50:32.172141", "last_filtered_by_keywords": "2024-06-04 15:30:34.490164", "last_approved_news": "2024-06-04 15:30:37.419586", "last_success_parsing": "2024-06-04 15:30:40.461885", "last_success_publishing": "2024-06-04 15:30:47.517012"}, {"host": "elpais.com/argentina", "url": "https://elpais.com/argentina/?ed=arg", "last_not_empty_rss": "2024-06-05 11:50:33.496543", "last_filtered_by_keywords": "2024-06-01 04:50:25.169718", "last_approved_news": null, "last_success_parsing": null, "last_success_publishing": null}, {"host": "irishexaminer.com", "url": "https://www.irishexaminer.com/", "last_not_empty_rss": "2024-06-05 11:50:33.679176", "last_filtered_by_keywords": "2024-06-04 14:20:27.387035", "last_approved_news": "2024-06-04 14:20:29.836616", "last_success_parsing": "2024-06-04 14:20:47.856603", "last_success_publishing": "2024-06-04 14:20:59.356017"}, {"host": "greekcitytimes.com", "url": "https://greekcitytimes.com/", "last_not_empty_rss": "2024-06-05 11:50:33.857052", "last_filtered_by_keywords": "2024-06-03 18:40:27.659971", "last_approved_news": "2024-06-02 03:50:25.595305", "last_success_parsing": "2024-06-02 03:50:43.313359", "last_success_publishing": null}, {"host": "infobae.com", "url": "https://www.infobae.com/", "last_not_empty_rss": "2024-06-05 10:50:42.923444", "last_filtered_by_keywords": "2024-06-05 10:50:41.374262", "last_approved_news": "2024-06-05 10:50:48.023081", "last_success_parsing": "2024-06-05 04:01:57.933757", "last_success_publishing": "2024-06-05 04:08:03.775762"}, {"host": "dw.com", "url": "https://www.dw.com/", "last_not_empty_rss": "2024-06-05 11:50:33.868922", "last_filtered_by_keywords": null, "last_approved_news": null, "last_success_parsing": null, "last_success_publishing": null}, {"host": "irishtimes.com", "url": "https://www.irishtimes.com/", "last_not_empty_rss": "2024-06-05 08:30:29.135945", "last_filtered_by_keywords": "2024-06-02 03:40:31.167445", "last_approved_news": "2024-06-02 03:40:33.090440", "last_success_parsing": "2024-06-02 03:40:50.729456", "last_success_publishing": "2024-06-02 03:40:59.043239"}, {"host": "molisenetwork.net", "url": "https://www.molisenetwork.net/", "last_not_empty_rss": "2024-06-05 11:50:34.787632", "last_filtered_by_keywords": null, "last_approved_news": null, "last_success_parsing": null, "last_success_publishing": null}, {"host": "jornada.com.mx", "url": "https://www.jornada.com.mx/", "last_not_empty_rss": "2024-06-05 11:50:35.148651", "last_filtered_by_keywords": "2024-06-04 10:40:27.880035", "last_approved_news": null, "last_success_parsing": null, "last_success_publishing": null}, {"host": "logist.today", "url": "https://logist.today/", "last_not_empty_rss": "2024-06-05 11:50:35.279885", "last_filtered_by_keywords": "2024-06-05 09:10:32.104678", "last_approved_news": "2024-06-05 09:10:35.070894", "last_success_parsing": null, "last_success_publishing": null}, {"host": "wszczecinie.pl", "url": "https://wszczecinie.pl/", "last_not_empty_rss": "2024-06-05 11:50:35.748761", "last_filtered_by_keywords": "2024-06-04 15:30:41.312262", "last_approved_news": null, "last_success_parsing": null, "last_success_publishing": null}, {"host": "okdiario.com", "url": "https://okdiario.com/", "last_not_empty_rss": "2024-06-05 11:50:36.263373", "last_filtered_by_keywords": "2024-06-04 19:30:32.583463", "last_approved_news": "2024-06-04 19:30:40.768087", "last_success_parsing": null, "last_success_publishing": null}, {"host": "nur.kz", "url": "https://www.nur.kz/", "last_not_empty_rss": "2024-06-05 11:50:36.293019", "last_filtered_by_keywords": "2024-06-05 07:10:34.226918", "last_approved_news": null, "last_success_parsing": null, "last_success_publishing": null}, {"host": "nn.ru", "url": "https://www.nn.ru/", "last_not_empty_rss": "2024-06-05 11:50:36.321364", "last_filtered_by_keywords": "2024-06-05 09:10:35.187163", "last_approved_news": null, "last_success_parsing": null, "last_success_publishing": null}, {"host": "tengrinews.kz", "url": "https://tengrinews.kz/", "last_not_empty_rss": "2024-06-05 11:50:36.323913", "last_filtered_by_keywords": "2024-06-04 13:20:35.235826", "last_approved_news": null, "last_success_parsing": null, "last_success_publishing": null}, {"host": "time.kz", "url": "https://time.kz/", "last_not_empty_rss": "2024-06-05 11:50:37.284792", "last_filtered_by_keywords": "2024-06-04 15:40:35.728179", "last_approved_news": null, "last_success_parsing": null, "last_success_publishing": null}, {"host": "unitetheunion.org", "url": "https://www.unitetheunion.org/", "last_not_empty_rss": "2024-06-04 22:40:33.719192", "last_filtered_by_keywords": "2024-06-04 16:00:41.957564", "last_approved_news": "2024-06-04 16:00:50.100889", "last_success_parsing": null, "last_success_publishing": null}, {"host": "sak.fi", "url": "https://www.sak.fi/", "last_not_empty_rss": "2024-06-05 11:50:37.318311", "last_filtered_by_keywords": "2024-06-05 07:40:32.945525", "last_approved_news": null, "last_success_parsing": null, "last_success_publishing": null}, {"host": "sputnik-georgia.ru", "url": "https://sputnik-georgia.ru/", "last_not_empty_rss": "2024-06-05 11:50:38.114981", "last_filtered_by_keywords": "2024-06-04 18:40:33.007666", "last_approved_news": null, "last_success_parsing": null, "last_success_publishing": null}, {"host": "currenttime.tv", "url": "https://www.currenttime.tv/", "last_not_empty_rss": "2024-06-05 11:43:11.537077", "last_filtered_by_keywords": "2024-06-04 12:30:49.508781", "last_approved_news": null, "last_success_parsing": null, "last_success_publishing": null}, {"host": "telegraph.co.uk", "url": "https://www.telegraph.co.uk/", "last_not_empty_rss": "2024-06-05 11:50:38.138217", "last_filtered_by_keywords": "2024-06-05 11:20:35.155162", "last_approved_news": "2024-06-01 23:00:37.319671", "last_success_parsing": null, "last_success_publishing": null}, {"host": "talouselama.fi", "url": "https://www.talouselama.fi/", "last_not_empty_rss": "2024-06-05 11:50:38.326924", "last_filtered_by_keywords": null, "last_approved_news": null, "last_success_parsing": null, "last_success_publishing": null}, {"host": "aljazeera.com", "url": "https://www.aljazeera.com/", "last_not_empty_rss": "2024-06-05 11:50:21.280343", "last_filtered_by_keywords": "2024-06-05 09:40:22.068770", "last_approved_news": "2024-06-04 21:00:32.031607", "last_success_parsing": "2024-06-03 16:40:23.144763", "last_success_publishing": "2024-06-03 16:40:30.488705"}, {"host": "eldiariocantabria.publico.es", "url": "https://eldiariocantabria.publico.es/", "last_not_empty_rss": "2024-06-05 11:50:21.752407", "last_filtered_by_keywords": "2024-06-05 11:20:25.107134", "last_approved_news": "2024-06-03 16:30:26.422752", "last_success_parsing": null, "last_success_publishing": null}, {"host": "reuters.com", "url": "https://www.reuters.com/", "last_not_empty_rss": "2024-06-05 11:50:38.620276", "last_filtered_by_keywords": "2024-06-05 10:30:34.562358", "last_approved_news": "2024-06-04 22:30:48.284551", "last_success_parsing": null, "last_success_publishing": null}, {"host": "dailysabah.com", "url": "https://www.dailysabah.com/", "last_not_empty_rss": "2024-06-05 09:40:22.721774", "last_filtered_by_keywords": "2024-06-05 07:40:18.143886", "last_approved_news": null, "last_success_parsing": null, "last_success_publishing": null}, {"host": "themayor.eu", "url": "https://www.themayor.eu/", "last_not_empty_rss": "2024-06-05 11:50:38.778559", "last_filtered_by_keywords": null, "last_approved_news": null, "last_success_parsing": null, "last_success_publishing": null}, {"host": "uusisuomi.fi", "url": "https://www.uusisuomi.fi/", "last_not_empty_rss": "2024-06-05 11:50:39.234181", "last_filtered_by_keywords": null, "last_approved_news": null, "last_success_parsing": null, "last_success_publishing": null}, {"host": "economist.com", "url": "https://www.economist.com/", "last_not_empty_rss": "2024-06-05 11:50:24.557153", "last_filtered_by_keywords": null, "last_approved_news": null, "last_success_parsing": null, "last_success_publishing": null}, {"host": "zab.tv", "url": "https://zab.tv/", "last_not_empty_rss": "2024-06-05 11:50:39.536002", "last_filtered_by_keywords": "2024-06-05 10:11:07.249927", "last_approved_news": null, "last_success_parsing": null, "last_success_publishing": null}, {"host": "yle.fi", "url": "https://yle.fi/", "last_not_empty_rss": "2024-06-05 11:50:40.041319", "last_filtered_by_keywords": "2024-06-04 14:40:35.815940", "last_approved_news": null, "last_success_parsing": null, "last_success_publishing": null}, {"host": "tbsnews.net", "url": "https://www.tbsnews.net/", "last_not_empty_rss": "2024-06-05 11:50:41.045715", "last_filtered_by_keywords": "2024-06-05 06:10:35.701554", "last_approved_news": null, "last_success_parsing": null, "last_success_publishing": null}, {"host": "trojmiasto.pl", "url": "https://www.trojmiasto.pl/", "last_not_empty_rss": "2024-06-05 11:50:41.717245", "last_filtered_by_keywords": "2024-06-03 20:30:33.317346", "last_approved_news": "2024-06-03 20:30:37.047035", "last_success_parsing": "2024-06-03 20:30:54.965455", "last_success_publishing": "2024-06-03 20:31:00.713938"}, {"host": "vedomosti.ru", "url": "https://www.vedomosti.ru/", "last_not_empty_rss": "2024-06-05 11:50:42.030093", "last_filtered_by_keywords": null, "last_approved_news": null, "last_success_parsing": null, "last_success_publishing": null}, {"host": "europapress.es", "url": "https://www.europapress.es/", "last_not_empty_rss": "2024-06-05 11:50:52.896782", "last_filtered_by_keywords": "2024-06-05 00:40:27.289424", "last_approved_news": "2024-06-05 00:40:31.101600", "last_success_parsing": "2024-06-05 00:40:33.842560", "last_success_publishing": "2024-06-05 00:40:43.323552"}, {"host": "nypost.com", "url": "https://nypost.com/", "last_not_empty_rss": null, "last_filtered_by_keywords": null, "last_approved_news": null, "last_success_parsing": null, "last_success_publishing": null}, {"host": "021.rs", "url": "https://www.021.rs/", "last_not_empty_rss": null, "last_filtered_by_keywords": null, "last_approved_news": null, "last_success_parsing": null, "last_success_publishing": null}, {"host": "newsvl.ru", "url": "https://www.newsvl.ru/", "last_not_empty_rss": "2024-06-05 11:51:33.218859", "last_filtered_by_keywords": null, "last_approved_news": null, "last_success_parsing": null, "last_success_publishing": null}, {"host": "industriall-union.org", "url": "https://www.industriall-union.org/", "last_not_empty_rss": "2024-06-05 11:50:25.651268", "last_filtered_by_keywords": "2024-06-05 10:00:29.626758", "last_approved_news": "2024-06-05 10:00:32.412016", "last_success_parsing": null, "last_success_publishing": null}, {"host": "forbes.ru", "url": "https://www.forbes.ru/", "last_not_empty_rss": "2024-06-05 11:50:25.978563", "last_filtered_by_keywords": "2024-06-04 01:10:25.288872", "last_approved_news": null, "last_success_parsing": null, "last_success_publishing": null}, {"host": "metropolitano.gal", "url": "https://metropolitano.gal/", "last_not_empty_rss": null, "last_filtered_by_keywords": null, "last_approved_news": null, "last_success_parsing": null, "last_success_publishing": null}, {"host": "ura.news", "url": "https://ura.news/", "last_not_empty_rss": "2024-06-05 11:50:42.885477", "last_filtered_by_keywords": "2024-06-05 11:30:38.951248", "last_approved_news": "2024-06-05 11:30:43.697829", "last_success_parsing": "2024-06-05 11:32:42.270878", "last_success_publishing": "2024-06-05 11:57:32.936148"}, {"host": "bnn-news.com", "url": "https://bnn-news.com/", "last_not_empty_rss": "2024-06-05 12:01:21.847910", "last_filtered_by_keywords": "2024-06-03 08:30:18.840615", "last_approved_news": "2024-06-03 08:30:21.990617", "last_success_parsing": "2024-06-03 08:30:39.809704", "last_success_publishing": "2024-06-03 08:31:36.431993"}, {"host": "cmkos.cz", "url": "https://www.cmkos.cz/", "last_not_empty_rss": "2024-06-05 12:01:22.529760", "last_filtered_by_keywords": "2024-06-03 11:50:19.984067", "last_approved_news": null, "last_success_parsing": null, "last_success_publishing": null}, {"host": "gazeta.ru", "url": "https://www.gazeta.ru/", "last_not_empty_rss": "2024-06-05 11:50:27.028538", "last_filtered_by_keywords": null, "last_approved_news": null, "last_success_parsing": null, "last_success_publishing": null}, {"host": "bssnews.net", "url": "https://www.bssnews.net/", "last_not_empty_rss": "2024-06-05 12:01:22.938207", "last_filtered_by_keywords": null, "last_approved_news": null, "last_success_parsing": null, "last_success_publishing": null}, {"host": "businesstimes.com.sg/singapore", "url": "https://www.businesstimes.com.sg/singapore", "last_not_empty_rss": "2024-06-05 12:01:23.457282", "last_filtered_by_keywords": "2024-06-05 11:10:15.388362", "last_approved_news": null, "last_success_parsing": null, "last_success_publishing": null}, {"host": "eleconomista.com.mx", "url": "https://www.eleconomista.com.mx/", "last_not_empty_rss": "2024-06-05 12:01:24.394741", "last_filtered_by_keywords": "2024-06-04 15:00:27.483731", "last_approved_news": null, "last_success_parsing": null, "last_success_publishing": null}, {"host": "elpais.com/america-colombia", "url": "https://elpais.com/america-colombia/?ed=col", "last_not_empty_rss": "2024-06-05 11:50:27.995707", "last_filtered_by_keywords": null, "last_approved_news": null, "last_success_parsing": null, "last_success_publishing": null}, {"host": "elperiodico.com", "url": "https://www.elperiodico.com/es/", "last_not_empty_rss": "2024-06-05 11:50:28.253794", "last_filtered_by_keywords": "2024-06-04 22:10:25.443110", "last_approved_news": "2024-06-03 10:00:46.515475", "last_success_parsing": "2024-06-03 10:01:05.078782", "last_success_publishing": "2024-06-03 10:01:13.648983"}, {"host": "greekreporter.com", "url": "https://greekreporter.com/", "last_not_empty_rss": "2024-06-05 11:50:28.893351", "last_filtered_by_keywords": null, "last_approved_news": null, "last_success_parsing": null, "last_success_publishing": null}, {"host": "citynews.ca", "url": "https://www.cbc.ca/", "last_not_empty_rss": "2024-06-05 12:01:24.954495", "last_filtered_by_keywords": "2024-06-05 02:40:15.664853", "last_approved_news": "2024-06-05 02:40:18.618555", "last_success_parsing": "2024-06-05 02:40:36.464695", "last_success_publishing": "2024-06-05 02:40:44.020683"}, {"host": "financialexpress.com", "url": "https://www.financialexpress.com/", "last_not_empty_rss": "2024-06-05 12:01:25.949486", "last_filtered_by_keywords": "2024-06-03 20:50:24.493727", "last_approved_news": null, "last_success_parsing": null, "last_success_publishing": null}, {"host": "elpais.com", "url": "https://elpais.com/", "last_not_empty_rss": "2024-06-05 12:01:27.280483", "last_filtered_by_keywords": "2024-06-05 04:10:23.152078", "last_approved_news": "2024-06-05 03:20:27.234812", "last_success_parsing": "2024-06-05 03:20:30.421484", "last_success_publishing": "2024-06-05 03:21:33.432367"}, {"host": "aif.ru", "url": "https://aif.ru/", "last_not_empty_rss": "2024-06-05 12:01:27.546801", "last_filtered_by_keywords": "2024-06-05 11:10:13.934085", "last_approved_news": null, "last_success_parsing": null, "last_success_publishing": null}, {"host": "money.pl", "url": "https://www.money.pl/", "last_not_empty_rss": "2024-06-05 11:50:29.399346", "last_filtered_by_keywords": "2024-06-05 09:40:26.934415", "last_approved_news": "2024-06-05 09:40:32.760663", "last_success_parsing": "2024-06-05 10:26:39.672729", "last_success_publishing": "2024-06-05 11:03:32.259773"}, {"host": "mixnews.lv", "url": "https://mixnews.lv/", "last_not_empty_rss": "2024-06-05 11:50:29.567703", "last_filtered_by_keywords": null, "last_approved_news": null, "last_success_parsing": null, "last_success_publishing": null}, {"host": "independent.co.uk", "url": "https://www.independent.co.uk/", "last_not_empty_rss": "2024-06-05 11:50:37.025825", "last_filtered_by_keywords": "2024-06-05 09:30:28.275635", "last_approved_news": "2024-06-04 11:50:32.886990", "last_success_parsing": "2024-06-04 11:50:51.157485", "last_success_publishing": "2024-06-04 11:51:36.159585"}, {"host": "rte.ie", "url": "https://www.rte.ie/", "last_not_empty_rss": "2024-06-05 11:50:37.488779", "last_filtered_by_keywords": "2024-06-04 06:10:34.966166", "last_approved_news": null, "last_success_parsing": null, "last_success_publishing": null}, {"host": "tribuneindia.com", "url": "https://www.tribuneindia.com/", "last_not_empty_rss": "2024-06-05 11:50:37.650537", "last_filtered_by_keywords": "2024-06-04 21:30:40.282218", "last_approved_news": "2024-06-04 21:30:42.443137", "last_success_parsing": null, "last_success_publishing": null}, {"host": "wsj.com", "url": "https://www.wsj.com/", "last_not_empty_rss": "2024-06-05 11:50:38.064111", "last_filtered_by_keywords": "2024-06-05 09:40:36.495145", "last_approved_news": "2024-06-04 12:10:37.908876", "last_success_parsing": null, "last_success_publishing": null}, {"host": "rosbalt.ru", "url": "https://www.rosbalt.ru/", "last_not_empty_rss": "2024-06-05 11:50:38.771784", "last_filtered_by_keywords": "2024-06-04 04:30:34.939365", "last_approved_news": null, "last_success_parsing": null, "last_success_publishing": null}, {"host": "apnews.com", "url": "https://apnews.com/", "last_not_empty_rss": "2024-06-05 11:50:15.354507", "last_filtered_by_keywords": "2024-06-05 10:20:19.694548", "last_approved_news": "2024-06-05 03:30:24.890765", "last_success_parsing": "2024-06-05 03:35:43.597503", "last_success_publishing": "2024-06-05 03:35:50.291782"}, {"host": "rg.ru", "url": "https://rg.ru/", "last_not_empty_rss": "2024-06-05 11:50:39.931000", "last_filtered_by_keywords": "2024-06-05 11:20:32.954293", "last_approved_news": "2024-06-04 10:00:44.858628", "last_success_parsing": "2024-06-04 10:01:16.929142", "last_success_publishing": "2024-06-04 10:01:23.112817"}, {"host": "washingtonpost.com", "url": "https://www.washingtonpost.com/", "last_not_empty_rss": "2024-06-05 11:50:40.799110", "last_filtered_by_keywords": "2024-06-05 06:10:41.887830", "last_approved_news": "2024-06-05 06:10:43.386975", "last_success_parsing": null, "last_success_publishing": null}, {"host": "mk.ru", "url": "https://www.mk.ru/", "last_not_empty_rss": "2024-06-05 11:50:40.063851", "last_filtered_by_keywords": "2024-06-05 11:50:41.527872", "last_approved_news": "2024-06-04 14:00:40.174181", "last_success_parsing": "2024-06-04 14:00:43.283355", "last_success_publishing": "2024-06-04 14:01:18.699063"}, {"host": "news.am", "url": "https://news.am/", "last_not_empty_rss": "2024-06-05 11:50:56.976521", "last_filtered_by_keywords": "2024-06-05 09:22:59.227118", "last_approved_news": "2024-06-04 10:31:01.906766", "last_success_parsing": "2024-06-04 10:31:20.858717", "last_success_publishing": "2024-06-04 10:44:36.792173"}, {"host": "dailymail.co.uk", "url": "https://www.dailyfinland.fi/", "last_not_empty_rss": "2024-06-05 11:50:18.790353", "last_filtered_by_keywords": "2024-06-05 10:30:29.024849", "last_approved_news": "2024-06-05 05:30:28.582799", "last_success_parsing": "2024-06-05 05:30:39.769986", "last_success_publishing": "2024-06-05 05:31:25.560872"}, {"host": "kommersant.ru", "url": "https://www.kommersant.ru/", "last_not_empty_rss": "2024-06-05 11:51:28.074731", "last_filtered_by_keywords": "2024-06-05 08:00:38.841177", "last_approved_news": "2024-06-04 12:00:42.149029", "last_success_parsing": "2024-06-04 12:00:46.101006", "last_success_publishing": "2024-06-04 12:00:53.808835"}, {"host": "balkaninsight.com", "url": "https://balkaninsight.com/", "last_not_empty_rss": "2024-06-05 11:50:19.631855", "last_filtered_by_keywords": "2024-06-04 13:40:14.681295", "last_approved_news": null, "last_success_parsing": null, "last_success_publishing": null}, {"host": "newsib.net", "url": "https://newsib.net/", "last_not_empty_rss": "2024-06-05 11:51:53.109457", "last_filtered_by_keywords": "2024-06-03 04:10:31.443321", "last_approved_news": null, "last_success_parsing": null, "last_success_publishing": null}, {"host": "ngs.ru", "url": "https://ngs.ru/", "last_not_empty_rss": "2024-06-05 11:53:00.577891", "last_filtered_by_keywords": "2024-06-04 11:41:59.137213", "last_approved_news": "2024-06-01 11:51:11.995642", "last_success_parsing": "2024-06-01 11:51:21.563128", "last_success_publishing": "2024-06-01 11:51:37.164197"}, {"host": "forbes.com", "url": "https://www.forbes.com/", "last_not_empty_rss": "2024-06-05 11:50:29.876439", "last_filtered_by_keywords": "2024-06-05 10:00:30.542565", "last_approved_news": "2024-06-05 10:00:36.673800", "last_success_parsing": "2024-06-05 11:33:35.506435", "last_success_publishing": "2024-06-05 11:57:22.556703"}, {"host": "iz.ru", "url": "https://iz.ru/", "last_not_empty_rss": "2024-06-05 11:50:34.197232", "last_filtered_by_keywords": "2024-06-05 11:20:27.185500", "last_approved_news": "2024-06-05 11:20:32.856512", "last_success_parsing": "2024-06-05 11:33:07.485544", "last_success_publishing": "2024-06-05 11:57:43.448663"}, {"host": "theguardian.com", "url": "https://www.theguardian.com/", "last_not_empty_rss": "2024-06-05 11:50:34.890763", "last_filtered_by_keywords": "2024-06-05 11:50:35.493699", "last_approved_news": "2024-06-05 11:50:38.523593", "last_success_parsing": "2024-06-05 11:33:02.460821", "last_success_publishing": "2024-06-05 11:58:53.010489"}, {"host": "zeit.de", "url": "https://www.zeit.de/", "last_not_empty_rss": "2024-06-05 11:50:42.614849", "last_filtered_by_keywords": "2024-06-05 09:30:38.036352", "last_approved_news": "2024-06-05 09:30:42.190144", "last_success_parsing": "2024-06-05 10:26:53.937316", "last_success_publishing": "2024-06-05 11:59:03.577353"}, {"host": "abc.net.au", "url": "https://www.abc.net.au/", "last_not_empty_rss": "2024-06-05 12:01:20.933167", "last_filtered_by_keywords": "2024-06-05 11:30:18.491546", "last_approved_news": null, "last_success_parsing": null, "last_success_publishing": null}, {"host": "bankfax.ru", "url": "https://www.bankfax.ru/", "last_not_empty_rss": "2024-06-05 12:01:21.532237", "last_filtered_by_keywords": "2024-06-05 02:00:22.258878", "last_approved_news": null, "last_success_parsing": null, "last_success_publishing": null}, {"host": "africanews.com", "url": "https://www.africanews.com/", "last_not_empty_rss": "2024-06-05 12:01:21.880293", "last_filtered_by_keywords": "2024-06-05 08:30:21.376142", "last_approved_news": "2024-06-05 08:30:24.815388", "last_success_parsing": "2024-06-05 10:26:36.237442", "last_success_publishing": null}, {"host": "ecfr.eu", "url": "https://ecfr.eu/", "last_not_empty_rss": "2024-06-05 11:50:23.529770", "last_filtered_by_keywords": null, "last_approved_news": null, "last_success_parsing": null, "last_success_publishing": null}, {"host": "bankier.pl", "url": "https://www.bankier.pl/", "last_not_empty_rss": "2024-06-05 12:01:23.538214", "last_filtered_by_keywords": "2024-06-05 04:10:20.070490", "last_approved_news": "2024-06-03 11:10:27.446439", "last_success_parsing": "2024-06-02 12:35:32.428720", "last_success_publishing": "2024-06-02 12:35:40.388088"}, {"host": "brusselstimes.com", "url": "https://www.brusselstimes.com/", "last_not_empty_rss": "2024-06-05 08:41:21.493246", "last_filtered_by_keywords": "2024-06-04 21:30:18.869305", "last_approved_news": null, "last_success_parsing": null, "last_success_publishing": null}, {"host": "businesstimes.com.sg/international", "url": "https://www.businesstimes.com.sg/international", "last_not_empty_rss": "2024-06-05 12:01:24.304954", "last_filtered_by_keywords": "2024-06-05 02:00:17.890986", "last_approved_news": "2024-06-04 04:30:30.237521", "last_success_parsing": "2024-06-04 04:30:35.423580", "last_success_publishing": "2024-06-04 04:31:34.718586"}, {"host": "cbc.ca", "url": "", "last_not_empty_rss": "2024-06-05 12:01:25.274188", "last_filtered_by_keywords": "2024-06-02 15:10:19.998646", "last_approved_news": null, "last_success_parsing": null, "last_success_publishing": null}, {"host": "cnn.com", "url": "https://edition.cnn.com/", "last_not_empty_rss": "2024-06-05 12:01:25.346739", "last_filtered_by_keywords": null, "last_approved_news": null, "last_success_parsing": null, "last_success_publishing": null}, {"host": "elespanol.com", "url": "https://www.elespanol.com/", "last_not_empty_rss": "2024-06-05 12:01:27.067291", "last_filtered_by_keywords": "2024-06-04 18:20:19.882765", "last_approved_news": "2024-06-04 18:20:23.616130", "last_success_parsing": "2024-06-04 18:20:41.302038", "last_success_publishing": "2024-06-04 18:21:25.301670"}, {"host": "france24.com", "url": "https://www.france24.com/", "last_not_empty_rss": "2024-06-05 12:01:27.318768", "last_filtered_by_keywords": "2024-06-04 17:20:22.836013", "last_approved_news": "2024-06-03 17:00:38.839878", "last_success_parsing": "2024-06-03 17:00:51.264012", "last_success_publishing": "2024-06-03 17:01:08.133698"}, {"host": "err.ee", "url": "https://www.err.ee/", "last_not_empty_rss": "2024-06-05 11:50:27.456655", "last_filtered_by_keywords": "2024-06-04 14:40:28.345869", "last_approved_news": null, "last_success_parsing": null, "last_success_publishing": null}, {"host": "helsinkitimes.fi", "url": "https://www.helsinkitimes.fi/", "last_not_empty_rss": "2024-06-05 12:01:28.664515", "last_filtered_by_keywords": null, "last_approved_news": null, "last_success_parsing": null, "last_success_publishing": null}, {"host": "montrealgazette.com", "url": "https://montrealgazette.com/", "last_not_empty_rss": "2024-06-05 11:50:28.857725", "last_filtered_by_keywords": "2024-06-04 22:10:30.308394", "last_approved_news": "2024-06-02 19:50:31.945479", "last_success_parsing": "2024-06-02 20:24:27.906679", "last_success_publishing": "2024-06-02 20:24:37.158676"}, {"host": "elpais.com/chile", "url": "https://elpais.com/chile/?ed=chl", "last_not_empty_rss": "2024-06-05 11:50:30.198725", "last_filtered_by_keywords": "2024-06-03 04:10:29.424241", "last_approved_news": "2024-05-31 10:00:28.869234", "last_success_parsing": "2024-05-31 10:00:32.719394", "last_success_publishing": null}, {"host": "politico.eu", "url": "https://www.politico.eu/", "last_not_empty_rss": "2024-06-05 11:50:30.287890", "last_filtered_by_keywords": "2024-06-04 15:10:32.955739", "last_approved_news": "2024-06-04 15:10:41.971209", "last_success_parsing": null, "last_success_publishing": null}, {"host": "mirror.co.uk", "url": "https://www.mirror.co.uk/", "last_not_empty_rss": "2024-06-05 11:50:30.523112", "last_filtered_by_keywords": "2024-06-05 11:30:37.378071", "last_approved_news": "2024-06-05 11:30:39.528563", "last_success_parsing": "2024-06-05 11:33:25.231853", "last_success_publishing": "2024-06-05 09:31:03.413823"}, {"host": "indiatoday.in", "url": "https://www.indiatoday.in/", "last_not_empty_rss": "2024-06-05 11:50:33.779307", "last_filtered_by_keywords": "2024-06-05 08:40:33.708205", "last_approved_news": "2024-06-05 08:40:36.628098", "last_success_parsing": "2024-06-04 06:45:43.855615", "last_success_publishing": "2024-06-01 11:41:06.142684"}, {"host": "ru.investing.com", "url": "https://ru.investing.com/", "last_not_empty_rss": "2024-06-05 11:50:33.925658", "last_filtered_by_keywords": "2024-06-04 17:00:38.454776", "last_approved_news": null, "last_success_parsing": null, "last_success_publishing": null}, {"host": "huffpost.com", "url": "https://www.huffpost.com/", "last_not_empty_rss": "2024-06-05 11:50:33.946379", "last_filtered_by_keywords": "2024-06-04 18:40:26.316124", "last_approved_news": null, "last_success_parsing": null, "last_success_publishing": null}, {"host": "novinite.com", "url": "https://www.novinite.com/", "last_not_empty_rss": "2024-06-05 11:50:34.002500", "last_filtered_by_keywords": "2024-06-04 21:00:38.478427", "last_approved_news": "2024-06-04 21:01:02.870362", "last_success_parsing": null, "last_success_publishing": null}, {"host": "rockpapershotgun.com", "url": "https://www.rockpapershotgun.com/", "last_not_empty_rss": "2024-06-05 11:50:34.645790", "last_filtered_by_keywords": "2024-06-05 09:40:28.837513", "last_approved_news": "2024-06-04 18:40:33.764347", "last_success_parsing": "2024-06-04 18:40:36.149607", "last_success_publishing": "2024-06-04 18:40:45.508898"}, {"host": "euractiv.com", "url": "http://www.euractiv.com/", "last_not_empty_rss": "2024-06-05 11:50:34.842065", "last_filtered_by_keywords": "2024-06-05 05:40:22.957110", "last_approved_news": "2024-06-05 05:10:24.825671", "last_success_parsing": "2024-06-05 05:10:32.153198", "last_success_publishing": "2024-06-05 05:12:50.454558"}, {"host": "larazon.es", "url": "https://www.larazon.es/", "last_not_empty_rss": "2024-06-05 11:50:35.261801", "last_filtered_by_keywords": "2024-06-03 16:50:30.618358", "last_approved_news": null, "last_success_parsing": null, "last_success_publishing": null}, {"host": "sky.com", "url": "https://www.sky.com/", "last_not_empty_rss": "2024-06-05 11:50:36.254694", "last_filtered_by_keywords": "2024-06-04 20:00:38.461848", "last_approved_news": "2024-06-04 20:00:40.591121", "last_success_parsing": "2024-05-31 11:41:02.235804", "last_success_publishing": null}, {"host": "orda.kz", "url": "https://orda.kz/", "last_not_empty_rss": "2024-06-05 11:50:36.687576", "last_filtered_by_keywords": "2024-06-05 11:10:37.310402", "last_approved_news": null, "last_success_parsing": null, "last_success_publishing": null}, {"host": "spiegel.de", "url": "https://www.spiegel.de/", "last_not_empty_rss": "2024-06-05 11:50:36.751275", "last_filtered_by_keywords": "2024-06-05 09:50:36.078508", "last_approved_news": "2024-06-03 09:00:47.819086", "last_success_parsing": "2024-06-03 09:00:50.119710", "last_success_publishing": "2024-06-03 05:40:53.901909"}, {"host": "publico.es", "url": "https://publico.es/", "last_not_empty_rss": "2024-06-05 11:50:36.992445", "last_filtered_by_keywords": "2024-06-05 10:11:29.110278", "last_approved_news": "2024-06-04 14:50:41.330230", "last_success_parsing": "2024-06-04 14:50:58.696502", "last_success_publishing": "2024-06-04 14:51:39.116164"}, {"host": "schengenvisainfo.com", "url": "https://www.schengenvisainfo.com/", "last_not_empty_rss": null, "last_filtered_by_keywords": null, "last_approved_news": null, "last_success_parsing": null, "last_success_publishing": null}, {"host": "rubaltic.ru", "url": "https://www.rubaltic.ru/", "last_not_empty_rss": null, "last_filtered_by_keywords": null, "last_approved_news": null, "last_success_parsing": null, "last_success_publishing": null}, {"host": "dailyfinland.fi", "url": "", "last_not_empty_rss": null, "last_filtered_by_keywords": null, "last_approved_news": null, "last_success_parsing": null, "last_success_publishing": null}]