[
    {
        "url": "https://news.am/rus/news/827878.html",
        "title": "Сотрудники Samsung впервые в истории компании устроили забастовку",
        "title_en": "Samsung employees went on strike for the first time in the company's history",
        "summary": "Забастовка происходит в Samsung Electronics, борющейся за доминирующие позиции в производстве чипов памяти.\r\nНациональный профсоюз Samsung Electronics (NSEU) заявил о невыходе сотрудников на работу в пятницу 7 июня.\r\nПереговоры о повышении зарплаты и премиях с руководством компании сорвались.\r\nЦель забастовки - провести конструктивный разговор с руководством.\r\nSamsung Electronics заявила, что забастовка не повлияла на производство и деловую активность компании.",
        "summary_en": "The strike is taking place at Samsung Electronics, which is fighting for a dominant position in the production of memory chips.\r\nThe National Samsung Electronics Union (NSEU) announced the absenteeism of employees on Friday, June 7.\r\nNegotiations on salary increases and bonuses with the company's management broke down.\r\nThe purpose of the strike is to have a constructive conversation with the management.\r\nSamsung Electronics said the strike did not affect the company's production and business activities.",
        "image": "https://news.am/img/news/82/78/78/default.jpg",
        "country": {
            "name": "южная корея",
            "flag": "🇰🇷"
        },
        "who": "заводские рабочие",
        "created": "2024-06-07 17:48:24.573210"
    }
]